branch.v
module branch
#(parameter BITS = 32)
(clk, instr, a, b, br);

    input         clk;
    input  [BITS-1:0] a;
    input  [BITS-1:0] b;
    input  [31:0]     instr;
    output        br;

    reg           br;

    initial 
        br = 0;

    always @(posedge clk) begin
        casex ({instr[14:12], instr[6:0]})
            10'b0001100011 : begin // BEQ
                                 br <= (a == b) ? 1 : 0; 
                             end  
            10'b0011100011 : begin // BNE
            		         br <= (a != b) ? 1 : 0; 
            		     end   
            10'b1001100011 : begin // BLT
                                 br <= ($signed(a) <  $signed(b)) ? 1 : 0; 
                             end  
            10'b1011100011 : begin // BGE
                                 br <= ($signed(a) >= $signed(b)) ? 1 : 0; 
                             end   
            10'b1101100011 : begin // BLTU
                                 br <= (a <  b) ? 1 : 0; 
                             end  
            10'b1111100011 : begin // BGEU
                                 br <= (a >= b) ? 1 : 0;
                             end   
            10'bxxx1101111 : begin // JAL
                                 br <= 1;
                             end
            10'b0001100111 : begin // JALR
                                 br <= 1;
                             end   
            default        : begin 
                                 br <= 0;
                             end
        endcase
    end

endmodule

tests/branchtest.v
module branchtest();
    reg         clk;
    reg  [31:0] instruction;
    reg  [31:0] a;
    reg  [31:0] b;
    wire        branch;
    
    initial begin
        $dumpfile("branchtest.vcd");
        $dumpvars(0, branchtest);
    end

    always #5 clk = !clk;

    branch #(.BITS(32)) branchtst(clk, instruction, a, b, branch);

    initial begin
        clk = 0;
        #0  instruction = 'bxxxxxxxxxxxxxxxxxxxxxxxxx1101111;
        #10 instruction = 'bxxxxxxxxxxxxxxxxxxxxxxxxx1100111;
        #10 instruction = 'bxxxxxxxxxxxxxxxxx000xxxxx1100011;
            a = 'hA;
            b = 'hB;
        #10 instruction = 'bxxxxxxxxxxxxxxxxx001xxxxx1100011;  
        #10 instruction = 'bxxxxxxxxxxxxxxxxx100xxxxx1100011;
        #10 instruction = 'bxxxxxxxxxxxxxxxxx101xxxxx1100011;
        #10 instruction = 'bxxxxxxxxxxxxxxxxx110xxxxx1100011;
        #10 instruction = 'bxxxxxxxxxxxxxxxxx111xxxxx1100011;
        #20 $finish;
    end

endmodule

tests/branchtest.vcd
$date
	Mon Oct 25 00:37:36 2021
$end
$version
	Icarus Verilog
$end
$timescale
	1s
$end
$scope module branchtest $end
$var wire 1 ! branch $end
$var reg 32 " a [31:0] $end
$var reg 32 # b [31:0] $end
$var reg 1 $ clk $end
$var reg 32 % instruction [31:0] $end
$scope module branchtst $end
$var wire 32 & a [31:0] $end
$var wire 32 ' b [31:0] $end
$var wire 1 $ clk $end
$var wire 32 ( instr [31:0] $end
$var reg 1 ! br $end
$upscope $end
$upscope $end
$enddefinitions $end
#0
$dumpvars
bx1101111 (
bx '
bx &
bx1101111 %
0$
bx #
bx "
0!
$end
#5
1!
1$
#10
0$
bx1100111 %
bx1100111 (
#15
1$
#20
0$
b1011 #
b1011 '
b1010 "
b1010 &
bx000xxxxx1100011 %
bx000xxxxx1100011 (
#25
0!
1$
#30
0$
bx001xxxxx1100011 %
bx001xxxxx1100011 (
#35
1!
1$
#40
0$
bx100xxxxx1100011 %
bx100xxxxx1100011 (
#45
1$
#50
0$
bx101xxxxx1100011 %
bx101xxxxx1100011 (
#55
0!
1$
#60
0$
bx110xxxxx1100011 %
bx110xxxxx1100011 (
#65
1!
1$
#70
0$
bx111xxxxx1100011 %
bx111xxxxx1100011 (
#75
0!
1$
