immgen.v
module immgen
#(parameter BITS = 32)
(clk, instr, imm_en, imm);

    input             clk;
    input  [31:0]     instr;
    output            imm_en;
    output [BITS-1:0] imm;

    reg               imm_en;
    reg    [BITS-1:0] imm;

    initial begin
        imm <= 'b0;
        imm_en <= 0;
    end

    always @(posedge clk) begin
        casex (instr[6:0])
            7'b00x0011 : begin         // I-type - LB, LH, LW, ALU imm
                            imm <= $signed(instr[31:20]);   
                            imm_en <= 1;
                        end
            7'b1100111: begin          // I-type - JALR
                            imm <= $signed(instr[31:20]);   
                            imm_en <= 1;
                        end
            7'b0100011 : begin         // S-type - SW, SH, SB
                            imm <= $signed({instr[31:25], instr[11:7]});
                            imm_en <= 1;
                        end         
            7'b0x10111 : begin         // U-type - AUIPC, LUI
                            imm <= $signed(instr[31:12]);   
                            imm_en <= 1;
                        end
            7'b1100011 : begin         // B-type - BRANCH
                            imm <= $signed({instr[31], instr[7], instr[30:25], 
                                            instr[11:8], 1'b0});   
                            imm_en <= 1;
                        end
            7'b1101111 : begin         // J-type - JAL
                            imm <= $signed({instr[31], instr[19:12], instr[20], 
                                            instr[30:21], 1'b0});
                            imm_en <= 1;
                        end
            default    : begin 
                            imm <= 32'b0;
                            imm_en <= 0;
                        end
        endcase
    end

endmodule

tests/immtest.v
module immtest();
	reg         clk;
    reg  [31:0] instruction;
    wire [31:0] immediate;
    wire        immediate_enable;
    
 	initial begin
		$dumpfile("immtest.vcd");
        $dumpvars(0, immtest);
	end

	always #5 clk = !clk;

	immgen #(.BITS(32)) immtst(clk, instruction, immediate_enable, immediate);

    initial begin
        clk = 0;
        #0  instruction = 'bxxxxxxxxxxxxxxxxxxxxxxxxx0110011;  // R-type
        #10 instruction = 'b100010001000xxxxxxxxxxxxx0000011;  // I-type
        #10 instruction = 'b1000100xxxxxxxxxxxxx010000100011;  // S-type
        #10 instruction = 'b0100000xxxxxxxxxxxxx010011100011;  // B-type
        #10 instruction = 'b10101010101010101010xxxxx0110111;  // U-type
        #10 instruction = 'b00001000100110101010xxxxx1101111;  // J-type
        #20 $finish;
    end
endmodule

tests/immtest.vcd
$date
	Sun Sep 19 20:41:55 2021
$end
$version
	Icarus Verilog
$end
$timescale
	1s
$end
$scope module immtest $end
$var wire 1 ! immediate_enable $end
$var wire 32 " immediate [31:0] $end
$var reg 1 # clk $end
$var reg 32 $ instruction [31:0] $end
$scope module immtst $end
$var wire 1 # clk $end
$var wire 32 % instr [31:0] $end
$var reg 32 & imm [31:0] $end
$var reg 1 ! imm_en $end
$upscope $end
$upscope $end
$enddefinitions $end
#0
$dumpvars
b0 &
bx0110011 %
bx0110011 $
0#
b0 "
0!
$end
#5
1#
#10
0#
b100010001000xxxxxxxxxxxxx0000011 $
b100010001000xxxxxxxxxxxxx0000011 %
#15
1!
b11111111111111111111100010001000 "
b11111111111111111111100010001000 &
1#
#20
0#
b1000100xxxxxxxxxxxxx010000100011 $
b1000100xxxxxxxxxxxxx010000100011 %
#25
1#
#30
0#
b100000xxxxxxxxxxxxx010011100011 $
b100000xxxxxxxxxxxxx010011100011 %
#35
b110000001000 "
b110000001000 &
1#
#40
0#
b10101010101010101010xxxxx0110111 $
b10101010101010101010xxxxx0110111 %
#45
b11111111111110101010101010101010 "
b11111111111110101010101010101010 &
1#
#50
0#
b1000100110101010xxxxx1101111 $
b1000100110101010xxxxx1101111 %
#55
b10101010100010001000 "
b10101010100010001000 &
1#
