mem.v
module mem
#(parameter BITS = 32)    
(clk, ad, we, b, rs);

    input            clk;
    input [BITS-1:0] ad;   // mem address 
    input            we;   // write enable
    input [2:0]      b;    // width
    inout [BITS-1:0] rs;   // mem data - read write port
    parameter file = "";
    integer i = 0;

    reg [7:0]      memory[4095:0];   // 4096 x 8-bit 
    reg [BITS-1:0] rs_data;

    initial begin
        for (i = 0; i < 4096; i = i + 1) begin
            memory[i] = 'b0;
        end
        rs_data = 'b0;
        $readmemh(file, memory, 0, 4095);
    end

    always @(posedge clk)
        if (we) begin
            memory[ad]     <= rs[7:0];
            memory[ad + 1] <= (b == 3'b001) || (b == 3'b010) || (b == 3'b011) ? 
                              rs[15:8]  : memory[ad + 1];
            memory[ad + 2] <= (b == 3'b010) || (b == 3'b011) ? 
                              rs[23:16] : memory[ad + 2];
            memory[ad + 3] <= (b == 3'b010) || (b == 3'b011) ? 
                              rs[31:24] : memory[ad + 3];
            if (BITS > 32) begin
                memory[ad + 4] <= (b == 3'b011) ? rs[39:32] : memory[ad + 4]; 
                memory[ad + 5] <= (b == 3'b011) ? rs[47:40] : memory[ad + 5]; 
                memory[ad + 6] <= (b == 3'b011) ? rs[55:48] : memory[ad + 6]; 
                memory[ad + 7] <= (b == 3'b011) ? rs[63:56] : memory[ad + 7]; 
            end
        end
        else begin
            case ({b})
                3'b000  : begin // LB
                              rs_data <= $signed(memory[ad]);             
                          end   
                3'b001  : begin // LH
                              rs_data <= $signed({memory[ad + 1], memory[ad]}); 
                          end   
                3'b010  : begin // LW
                              rs_data <= $signed({memory[ad + 3], memory[ad + 2], 
                                                  memory[ad + 1], memory[ad]}); 
                          end   
                3'b011  : begin // LD
                              rs_data <= $signed({memory[ad + 7], memory[ad + 6], 
                                                  memory[ad + 5], memory[ad + 4],
                                                  memory[ad + 3], memory[ad + 2], 
                                                  memory[ad + 1], memory[ad]}); 
                          end   
                3'b100  : begin // LBU
                              rs_data <= {memory[ad]};
                          end   
                3'b101  : begin // LHU
                              rs_data <= {memory[ad + 1], memory[ad]};
                          end   
                3'b110  : begin // LWU
                              rs_data <= {memory[ad + 3], memory[ad + 2], 
                                          memory[ad + 1], memory[ad]};
                          end
                default : begin 
                              rs_data <= 'b0; 
                          end
            endcase
        end
            
    assign rs = (we) ? 'bz : rs_data;

endmodule

tests/memtest.v
module memtest();
	reg         clk;
    reg  [63:0] address;
    reg  [63:0] data;
    wire [63:0] data_wire;
    reg  [2:0]  width;
    reg         write_enable;
    
 	initial begin
		$dumpfile("memtest.vcd");
        $dumpvars(0, memtest);
	end

	always #5 clk = !clk;

	mem #(.BITS(64)) memtst(clk, address, write_enable, width, data_wire);
    defparam memtst.file = "memtest.mem";

    assign data_wire = write_enable ? data : 'bz;

    initial begin
        clk = 0;
        #0  address = 'h000000000000000;
            write_enable = 0;
            width = 'b000; 
        #10 width += 'b1;
        #10 width += 'b1;
        #10 width += 'b1;
        #10 address += 'h8;
            width = 'b000;
        #10 width = 'b100;
        #20 address = 'b0;
            width = 'b010;
            write_enable = 'b1;
            data  = 'hAAAAAAAABBBBBBBB;
        #10 write_enable = 'b0;
        #10 width = 'b110;
        #10 width = 'b011;
        #20 $finish;
    end
endmodule

tests/memtest.vcd
$date
	Sun Sep 19 19:56:21 2021
$end
$version
	Icarus Verilog
$end
$timescale
	1s
$end
$scope module memtest $end
$var wire 64 ! data_wire [63:0] $end
$var reg 64 " address [63:0] $end
$var reg 1 # clk $end
$var reg 64 $ data [63:0] $end
$var reg 3 % width [2:0] $end
$var reg 1 & write_enable $end
$scope module memtst $end
$var wire 64 ' ad [63:0] $end
$var wire 3 ( b [2:0] $end
$var wire 1 # clk $end
$var wire 64 ) rs [63:0] $end
$var wire 1 & we $end
$var reg 64 * rs_data [63:0] $end
$var integer 32 + i [31:0] $end
$upscope $end
$upscope $end
$enddefinitions $end
#0
$dumpvars
b1000000000000 +
b0 *
b0 )
b0 (
b0 '
0&
b0 %
bx $
0#
b0 "
b0 !
$end
#5
1#
#10
0#
b1 %
b1 (
#15
b1000100000000 !
b1000100000000 )
b1000100000000 *
1#
#20
0#
b10 %
b10 (
#25
b110011001000100001000100000000 !
b110011001000100001000100000000 )
b110011001000100001000100000000 *
1#
#30
0#
b11 %
b11 (
#35
b111011101100110010101010100010000110011001000100001000100000000 !
b111011101100110010101010100010000110011001000100001000100000000 )
b111011101100110010101010100010000110011001000100001000100000000 *
1#
#40
0#
b0 %
b0 (
b1000 "
b1000 '
#45
b1111111111111111111111111111111111111111111111111111111110001000 !
b1111111111111111111111111111111111111111111111111111111110001000 )
b1111111111111111111111111111111111111111111111111111111110001000 *
1#
#50
0#
b100 %
b100 (
#55
b10001000 !
b10001000 )
b10001000 *
1#
#60
0#
#65
1#
#70
b1010101010101010101010101010101010111011101110111011101110111011 !
b1010101010101010101010101010101010111011101110111011101110111011 )
0#
b1010101010101010101010101010101010111011101110111011101110111011 $
1&
b10 %
b10 (
b0 "
b0 '
#75
1#
#80
b10001000 !
b10001000 )
0#
0&
#85
b1111111111111111111111111111111110111011101110111011101110111011 !
b1111111111111111111111111111111110111011101110111011101110111011 )
b1111111111111111111111111111111110111011101110111011101110111011 *
1#
#90
0#
b110 %
b110 (
#95
b10111011101110111011101110111011 !
b10111011101110111011101110111011 )
b10111011101110111011101110111011 *
1#
#100
0#
b11 %
b11 (
#105
b111011101100110010101010100010010111011101110111011101110111011 !
b111011101100110010101010100010010111011101110111011101110111011 )
b111011101100110010101010100010010111011101110111011101110111011 *
1#
