regfile.v
module regfile
#(parameter BITS = 32)
(clk, ad1, ad2, adw, we, rs1, rs2, rsw);

    input             clk;
    input  [4:0]      ad1;  // rs1 address - read
    input  [4:0]      ad2;  // rs2 address - read
    input  [4:0]      adw;  // write port address
    input             we;   // write enable
    output [BITS-1:0] rs1;  // rs1 data 
    output [BITS-1:0] rs2;  // rs2 data 
    input  [BITS-1:0] rsw;  // write port data

    // Register file storage
    reg [BITS-1:0] registers[31:0]; // 32 x 32-bit
    reg [BITS-1:0] rs1;
    reg [BITS-1:0] rs2;

    integer i;

    initial begin
        for (i = 0; i < 32; i = i + 1) begin
            registers[i] <= 'b0;
        end
    end

    always @(posedge clk) begin
            registers[adw] = we ? rsw : registers[adw];
            rs1 <= (ad1) ? registers[ad1] : 'b0;
            rs2 <= (ad2) ? registers[ad2] : 'b0;
    end
endmodule

tests/regtest.v
module regtest();
    reg         clk;
    reg  [4:0]  address_a;
    reg  [4:0]  address_b;
    reg  [4:0]  address_write;
    reg         write_enable;
    wire [31:0] data_a;
    wire [31:0] data_b;
    reg  [31:0] data_write;

    initial begin
        $dumpfile("regtest.vcd");
        $dumpvars(0, regtest);
    end

    always #5 clk = !clk;

    regfile #(.BITS(32)) rftst(clk, address_a, address_b, address_write, write_enable, data_a, data_b, data_write);

    initial begin
        clk = 0;
        #0  data_write = 'haabbccdd;
            address_write = 'h01;
            write_enable = 'b1;
        #15 address_a = 'h01;
            address_b = 'h02;
            data_write = 'haaaaaaaa;
        #2  address_b = 'h01;
        #3  address_b = 'h02;
            data_write = 'hffffffff;
            address_write = 'h02;
            write_enable = 'b1;
        #8  data_write = 'ha0a0a0a0;
        #2  data_write = 'h12345678;
            address_write = 'h00;
        #10 address_b = 'h0;
            write_enable = 'b0;
        #10 address_a = 'h02;
            address_b = 'h01;
        #20 $finish;
    end
endmodule

tests/regtest.vcd
$date
	Sun Sep 19 20:16:15 2021
$end
$version
	Icarus Verilog
$end
$timescale
	1s
$end
$scope module regtest $end
$var wire 32 ! data_b [31:0] $end
$var wire 32 " data_a [31:0] $end
$var reg 5 # address_a [4:0] $end
$var reg 5 $ address_b [4:0] $end
$var reg 5 % address_write [4:0] $end
$var reg 1 & clk $end
$var reg 32 ' data_write [31:0] $end
$var reg 1 ( write_enable $end
$scope module rftst $end
$var wire 5 ) ad1 [4:0] $end
$var wire 5 * ad2 [4:0] $end
$var wire 5 + adw [4:0] $end
$var wire 1 & clk $end
$var wire 32 , rsw [31:0] $end
$var wire 1 ( we $end
$var reg 32 - rs1 [31:0] $end
$var reg 32 . rs2 [31:0] $end
$var integer 32 / i [31:0] $end
$upscope $end
$upscope $end
$enddefinitions $end
#0
$dumpvars
b100000 /
bx .
bx -
b10101010101110111100110011011101 ,
b1 +
bx *
bx )
1(
b10101010101110111100110011011101 '
0&
b1 %
bx $
bx #
bx "
bx !
$end
#5
1&
#10
0&
#15
b0 !
b0 .
b10101010101010101010101010101010 "
b10101010101010101010101010101010 -
1&
b10101010101010101010101010101010 '
b10101010101010101010101010101010 ,
b10 $
b10 *
b1 #
b1 )
#20
0&
b10 %
b10 +
b11111111111111111111111111111111 '
b11111111111111111111111111111111 ,
#25
b11111111111111111111111111111111 !
b11111111111111111111111111111111 .
1&
#28
b10100000101000001010000010100000 '
b10100000101000001010000010100000 ,
#30
b0 %
b0 +
b10010001101000101011001111000 '
b10010001101000101011001111000 ,
0&
#35
1&
#40
0&
0(
b0 $
b0 *
#45
b0 !
b0 .
1&
#50
0&
b1 $
b1 *
b10 #
b10 )
#55
b10101010101010101010101010101010 !
b10101010101010101010101010101010 .
b11111111111111111111111111111111 "
b11111111111111111111111111111111 -
1&
